obsELN/.DS_Store
obsELN/__init__.py
obsELN/__main__.py
obsELN/gui/obsidian_import_gui.py
obsELN/note/.DS_Store
obsELN/note/__init__.py
obsELN/note/analysis.py
obsELN/plot/__init__.py
obsELN/plot/sciplots.py
obsELN/plot/uplot.py
obsELN/reader/.DS_Store
obsELN/reader/__init__.py
obsELN/reader/biologic.py
obsELN/reader/eln.py
obsELN/reader/frontmatter.py
obsELN/reader/horiba.py
obsELN/reader/smartsem.py
obsELN/resources/.DS_Store
obsELN/resources/analysis_fm.yaml
obsELN/resources/analysis_template.md
obsELN/resources/biologic_mpt.yaml
obsELN/resources/chartsview_E_vs_Q_template.md
obsELN/resources/experimental_settings.md
obsELN/resources/gcpl_data_live_preview.md
obsELN/resources/gcpl_data_preview.md
obsELN/resources/instruments.yaml
obsELN/resources/labspec_txt.yaml
obsELN/resources/plot_colors.yaml
obsELN/resources/plot_styles.yaml
obsELN/resources/raman_data_preview.md
obsELN/resources/reload_icon.png
obsELN/resources/reload_icon.svg
obsELN/resources/reload_icon_2.svg
obsELN/resources/settings.yaml
obsELN/resources/smartsem_tiff.yaml
obseln-0.1.11.dist-info/LICENCE
obseln-0.1.11.dist-info/METADATA
obseln-0.1.11.dist-info/WHEEL
obseln-0.1.11.dist-info/RECORD
