Metadata-Version: 2.1
Name: obsELN
Version: 0.1.11
Summary: Tool to import and export analytical data into Obsidian ELN
License: GPL-3.0-or-later
Author: Frieder Scheiba
Author-email: frieder.scheiba@kit.edu
Requires-Python: >=3.10
Classifier: License :: OSI Approved :: GNU General Public License v3 or later (GPLv3+)
Classifier: Programming Language :: Python :: 3
Classifier: Programming Language :: Python :: 3.10
Classifier: Programming Language :: Python :: 3.11
Classifier: Programming Language :: Python :: 3.12
Requires-Dist: PyQt5 (>=5.10)
Requires-Dist: PyYAML (>=6.0)
Requires-Dist: matplotlib (>=3.8)
Requires-Dist: numpy (>=1.20)
Requires-Dist: pandas (>=2.2)
Requires-Dist: pillow (>=10.2.0)
Requires-Dist: ruamel.yaml (>=0.18)
Requires-Dist: tqdm (>=4.65)
